modelspace/__init__.py
recflow/__init__.py
reczoo/__init__.py
modelspace-0.0.0.dist-info/METADATA
modelspace-0.0.0.dist-info/WHEEL
modelspace-0.0.0.dist-info/top_level.txt
modelspace-0.0.0.dist-info/RECORD
